{
    "poll_list": [],
    "discourse_list": [
        {
            "thread_link": "https://ethereum-magicians.org/t/i-created-lottery-smart-contract/9986",
            "title": "I created lottery smart contract ",
            "index": 9986,
            "category": [
                "EIPs"
            ],
            "tags": [
                "evm"
            ],
            "content": [
                {
                    "author_link": "https://ethereum-magicians.org/u/PeterTakahashi",
                    "index": "1",
                    "likes": "0",
                    "time": "19/07/2022-04:32:36",
                    "content": "By using ERC20 tokens on an EVM-compatible public blockchain to play the lottery Lotteries can be conducted at low cost, with strict privacy, high return rates, and traceability guaranteed, without having to go through a lottery management organization. Winners are determined by randomly generated numbers on the blockchain. How do you think lottery contract? smart contract code   GitHub    GitHub - Foxlottery/foxlottery-v1: smart contract code smart contract code. Contribute to Foxlottery/foxlottery-v1 development by creating an account on GitHub.      whitepaper https://whitepaper.foxlottery.org/en.html ",
                    "links": [
                        "https://github.com/Foxlottery/foxlottery-v1",
                        "https://whitepaper.foxlottery.org/en.html"
                    ],
                    "GPT-summary": "The author of the post is explaining their proposal for a lottery smart contract using ERC20 tokens on a public blockchain. They provide links to the smart contract code and whitepaper. A 3rd party is asked for feedback on the lottery contract and the post also includes an advertisement for the smart contract. Additionally, the post invites questions about the proposal and constructive criticism.",
                    "GPT-proposal-categories": [
                        "Smart contract updates",
                        "Token economics",
                        "Privacy, Security and risk management",
                        "Interoperability and Scaleability",
                        "None"
                    ],
                    "GPT-discussion-categories": [
                        "Author of proposal is explaining proposal",
                        "3rd party or author is advertising proposal"
                    ],
                    "Sentiment": 5.323214285714286
                },
                {
                    "author_link": "https://ethereum-magicians.org/u/alireza.asadi",
                    "index": "2",
                    "likes": "0",
                    "time": "19/07/2022-06:26:12",
                    "content": "Nice job! I have just noticed your ILottery interface only have one method and missing the other methods of your contract. ",
                    "links": [],
                    "GPT-discussion-categories": null,
                    "Sentiment": 5.53125
                }
            ]
        }
    ],
    "group_index": "1832"
}