{
    "poll_list": [],
    "discourse_list": [
        {
            "thread_link": "https://forum.makerdao.com/t/mkr-compensation-working-group-membership/7460",
            "title": "MKR Compensation Working Group Membership ",
            "index": 7460,
            "category": [
                "Governance"
            ],
            "tags": [
                "mkr-compensation-wg"
            ],
            "content": [
                {
                    "author_link": "https://forum.makerdao.com/u/LongForWisdom",
                    "index": "#1",
                    "likes": "4",
                    "time": "12/04/2021-18:28:34",
                    "content": "As discussed previously, the path we\u2019re taking to resolve MKR Compensation is to setup a working group with five members from various stakeholder groups. These stakeholder groups and those chosen to fill them are listed below. This list will be updated as membership is determined. Current Core Unit Facilitator / Member  @LongForWisdom   Proposed Core Unit Facilitator / Member  @Derek   Large MKR Holder  @Planet_X   Community Member with little / no MKR  @Aes   Neutral 3rd Party Undecided - No candidates yet.  ",
                    "links": [
                        "https://forum.makerdao.com/t/maker-relay-ep-52-en-espanol/9209",
                        "https://forum.makerdao.com/t/maker-relay-ep-52/9191",
                        "https://forum.makerdao.com/t/mip40c3-sp79-mkr-compensation-for-starkenet-engineering-core-unit-sne-001/17042/29",
                        "https://forum.makerdao.com/t/operational-support-weekly-update-april-9-15-2021/7510",
                        "https://forum.makerdao.com/t/wanted-framework-for-mkr-compensation-working-group-proposed-core-units-representative/7265/11",
                        "https://forum.makerdao.com/t/agenda-discussion-scientific-governance-and-risk-137-thursday-april-15-17-00-utc/7384/4",
                        "https://forum.makerdao.com/t/maker-relay-ep-53-en-espanol/9330"
                    ],
                    "GPT-summary": "The post explains the plan to resolve MKR Compensation by setting up a working group with five members from various stakeholder groups. The author is explaining the proposal and the post also mentions the stakeholders who will be part of the working group. A neutral 3rd party is yet to be decided and the post invites feedback and questions.",
                    "GPT-proposal-categories": null,
                    "GPT-discussion-categories": [
                        "Author of proposal is explaining proposal"
                    ],
                    "Sentiment": 4.8834325396825395
                },
                {
                    "author_link": "https://forum.makerdao.com/u/ultraschuppi",
                    "index": "#2",
                    "likes": "1",
                    "time": "12/04/2021-18:30:46",
                    "content": "I think @Aes is the best choice from the community part, I therefore withdraw ",
                    "links": [],
                    "GPT-discussion-categories": null,
                    "Sentiment": 10.0
                },
                {
                    "author_link": "https://forum.makerdao.com/u/LongForWisdom",
                    "index": "#3",
                    "likes": "1",
                    "time": "12/04/2021-18:31:50",
                    "content": "Aight, I\u2019ve removed you  ",
                    "links": [],
                    "GPT-discussion-categories": null,
                    "Sentiment": 5.0
                },
                {
                    "author_link": "https://forum.makerdao.com/u/juan",
                    "index": "#4",
                    "likes": "0",
                    "time": "15/04/2021-15:50:53",
                    "content": "    LongForWisdom:  Neutral 3rd Party Undecided - No candidates yet.   I know that we were all hoping that @EthWarrior would lend us one of their best peeps to help with this, but since that\u2019s unlikely, maybe we can replace this category with another one? ",
                    "links": [],
                    "GPT-discussion-categories": [
                        "3rd party asking questions about proposal",
                        "3rd party giving constructive criticism of proposal",
                        "None of the topics listed match",
                        "None of the topics listed match"
                    ],
                    "Sentiment": 5.833333333333334
                },
                {
                    "author_link": "https://forum.makerdao.com/u/psychonaut",
                    "index": "#5",
                    "likes": "0",
                    "time": "15/04/2021-21:04:20",
                    "content": "I know this is a bit off-topic, but I stumbled upon the compensation agreement used by The Ready. ",
                    "links": [
                        "https://theready.com/"
                    ],
                    "GPT-discussion-categories": null,
                    "Sentiment": 6.0
                },
                {
                    "author_link": "https://forum.makerdao.com/u/system",
                    "index": "#6",
                    "likes": "0",
                    "time": "16/07/2021-03:04:29",
                    "content": "This topic was automatically closed 91 days after the last reply. New replies are no longer allowed. ",
                    "links": [],
                    "GPT-discussion-categories": null,
                    "Sentiment": 5.0606060606060606
                }
            ]
        }
    ]
}